{
  "summary": {
    "date": "2026-05-13",
    "total_filings": 39,
    "by_category": {
      "Large Shareholder": 19,
      "Share Buyback": 12,
      "Extraordinary Report": 8
    },
    "top_categories": [
      "Large Shareholder",
      "Share Buyback",
      "Extraordinary Report"
    ],
    "source": "EDINET (Financial Services Agency of Japan)",
    "generated_at": "2026-05-13T01:37:48.668369Z"
  },
  "filings": [
    {
      "doc_id": "S100Y30C",
      "doc_type": "Share Buyback Status Report",
      "doc_type_code": "220",
      "category": "Share Buyback",
      "company_jp": "株式会社ＰＡＬＴＡＣ",
      "company_en": "PALTAC Co., Ltd.",
      "description": "自己株券買付状況報告書（法２４条の６第１項に基づくもの）",
      "submitted_at": "2026-05-13 09:00",
      "edinet_code": "E02691",
      "sec_code": "82830",
      "doc_url": "https://disclosure2.edinet-fsa.go.jp/WZEK0040.aspx?S1_S100Y30C"
    },
    {
      "doc_id": "S100Y39W",
      "doc_type": "Share Buyback Status Report",
      "doc_type_code": "220",
      "category": "Share Buyback",
      "company_jp": "ＺＡＣＲＯＳ株式会社",
      "company_en": "ZACROS Co., Ltd.",
      "description": "自己株券買付状況報告書（法２４条の６第１項に基づくもの）",
      "submitted_at": "2026-05-13 09:00",
      "edinet_code": "E02423",
      "sec_code": "79170",
      "doc_url": "https://disclosure2.edinet-fsa.go.jp/WZEK0040.aspx?S1_S100Y39W"
    },
    {
      "doc_id": "S100Y2H4",
      "doc_type": "Extraordinary Report (Domestic Specified Securities)",
      "doc_type_code": "180",
      "category": "Extraordinary Report",
      "company_jp": "アセットマネジメントＯｎｅ株式会社",
      "company_en": "Asset Management One Co., Ltd.",
      "description": "臨時報告書（内国特定有価証券）",
      "submitted_at": "2026-05-13 09:02",
      "edinet_code": "E10677",
      "sec_code": null,
      "doc_url": "https://disclosure2.edinet-fsa.go.jp/WZEK0040.aspx?S1_S100Y2H4"
    },
    {
      "doc_id": "S100Y2RD",
      "doc_type": "Share Buyback Status Report",
      "doc_type_code": "220",
      "category": "Share Buyback",
      "company_jp": "株式会社南陽",
      "company_en": "Nanyo Co., Ltd.",
      "description": "自己株券買付状況報告書（法２４条の６第１項に基づくもの）",
      "submitted_at": "2026-05-13 09:03",
      "edinet_code": "E02792",
      "sec_code": "74170",
      "doc_url": "https://disclosure2.edinet-fsa.go.jp/WZEK0040.aspx?S1_S100Y2RD"
    },
    {
      "doc_id": "S100XRTZ",
      "doc_type": "Extraordinary Report (Domestic Specified Securities)",
      "doc_type_code": "180",
      "category": "Extraordinary Report",
      "company_jp": "三井住友ＤＳアセットマネジメント株式会社",
      "company_en": "Sumitomo Mitsui DS Asset Management Co., Ltd.",
      "description": "臨時報告書（内国特定有価証券）",
      "submitted_at": "2026-05-13 09:04",
      "edinet_code": "E08957",
      "sec_code": null,
      "doc_url": "https://disclosure2.edinet-fsa.go.jp/WZEK0040.aspx?S1_S100XRTZ"
    },
    {
      "doc_id": "S100Y2KO",
      "doc_type": "Extraordinary Report (Domestic Specified Securities)",
      "doc_type_code": "180",
      "category": "Extraordinary Report",
      "company_jp": "ブラックロック・ジャパン株式会社",
      "company_en": "BlackRock Japan Co., Ltd.",
      "description": "臨時報告書（内国特定有価証券）",
      "submitted_at": "2026-05-13 09:05",
      "edinet_code": "E09096",
      "sec_code": null,
      "doc_url": "https://disclosure2.edinet-fsa.go.jp/WZEK0040.aspx?S1_S100Y2KO"
    },
    {
      "doc_id": "S100Y3CH",
      "doc_type": "Amendment to Large Shareholder Report",
      "doc_type_code": "360",
      "category": "Large Shareholder",
      "company_jp": "株式会社深勝興産",
      "company_en": "Fukakatsu Kosan Co., Ltd.",
      "description": "訂正報告書（大量保有報告書・変更報告書）",
      "submitted_at": "2026-05-13 09:05",
      "edinet_code": "E27174",
      "sec_code": null,
      "doc_url": "https://disclosure2.edinet-fsa.go.jp/WZEK0040.aspx?S1_S100Y3CH"
    },
    {
      "doc_id": "S100Y2KW",
      "doc_type": "Extraordinary Report (Domestic Specified Securities)",
      "doc_type_code": "180",
      "category": "Extraordinary Report",
      "company_jp": "ブラックロック・ジャパン株式会社",
      "company_en": "BlackRock Japan Co., Ltd.",
      "description": "臨時報告書（内国特定有価証券）",
      "submitted_at": "2026-05-13 09:06",
      "edinet_code": "E09096",
      "sec_code": null,
      "doc_url": "https://disclosure2.edinet-fsa.go.jp/WZEK0040.aspx?S1_S100Y2KW"
    },
    {
      "doc_id": "S100Y1TG",
      "doc_type": "Extraordinary Report (Domestic Specified Securities)",
      "doc_type_code": "180",
      "category": "Extraordinary Report",
      "company_jp": "アムンディ・ジャパン株式会社",
      "company_en": "Amundi Japan Co., Ltd.",
      "description": "臨時報告書（内国特定有価証券）",
      "submitted_at": "2026-05-13 09:08",
      "edinet_code": "E09666",
      "sec_code": null,
      "doc_url": "https://disclosure2.edinet-fsa.go.jp/WZEK0040.aspx?S1_S100Y1TG"
    },
    {
      "doc_id": "S100XXHV",
      "doc_type": "Large Shareholder Report / Amendment",
      "doc_type_code": "350",
      "category": "Large Shareholder",
      "company_jp": "中村　克久",
      "company_en": "Katsuhisa Nakamura",
      "description": "大量保有報告書",
      "submitted_at": "2026-05-13 09:26",
      "edinet_code": "E41652",
      "sec_code": null,
      "doc_url": "https://disclosure2.edinet-fsa.go.jp/WZEK0040.aspx?S1_S100XXHV"
    },
    {
      "doc_id": "S100Y3EF",
      "doc_type": "Large Shareholder Report / Amendment",
      "doc_type_code": "350",
      "category": "Large Shareholder",
      "company_jp": "公益財団法人平和堂財団",
      "company_en": "Heiwado Foundation Public Interest Incorporated Foundation",
      "description": "変更報告書",
      "submitted_at": "2026-05-13 09:26",
      "edinet_code": "E35458",
      "sec_code": null,
      "doc_url": "https://disclosure2.edinet-fsa.go.jp/WZEK0040.aspx?S1_S100Y3EF"
    },
    {
      "doc_id": "S100Y3FJ",
      "doc_type": "Share Buyback Status Report",
      "doc_type_code": "220",
      "category": "Share Buyback",
      "company_jp": "東京瓦斯株式会社",
      "company_en": "Tokyo Gas Co., Ltd.",
      "description": "自己株券買付状況報告書（法２４条の６第１項に基づくもの）",
      "submitted_at": "2026-05-13 09:28",
      "edinet_code": "E04514",
      "sec_code": "95310",
      "doc_url": "https://disclosure2.edinet-fsa.go.jp/WZEK0040.aspx?S1_S100Y3FJ"
    },
    {
      "doc_id": "S100Y3ET",
      "doc_type": "Extraordinary Report (Domestic Specified Securities)",
      "doc_type_code": "180",
      "category": "Extraordinary Report",
      "company_jp": "マクセル株式会社",
      "company_en": "Maxell Co., Ltd.",
      "description": "臨時報告書",
      "submitted_at": "2026-05-13 09:30",
      "edinet_code": "E01947",
      "sec_code": "68100",
      "doc_url": "https://disclosure2.edinet-fsa.go.jp/WZEK0040.aspx?S1_S100Y3ET"
    },
    {
      "doc_id": "S100Y2DQ",
      "doc_type": "Large Shareholder Report / Amendment",
      "doc_type_code": "350",
      "category": "Large Shareholder",
      "company_jp": "夏原　行平",
      "company_en": "Yukihira Natsuhara",
      "description": "変更報告書",
      "submitted_at": "2026-05-13 09:30",
      "edinet_code": "E38115",
      "sec_code": null,
      "doc_url": "https://disclosure2.edinet-fsa.go.jp/WZEK0040.aspx?S1_S100Y2DQ"
    },
    {
      "doc_id": "S100Y2HC",
      "doc_type": "Share Buyback Status Report",
      "doc_type_code": "220",
      "category": "Share Buyback",
      "company_jp": "株式会社シイエム・シイ",
      "company_en": "CM Co., Ltd.",
      "description": "自己株券買付状況報告書（法２４条の６第１項に基づくもの）",
      "submitted_at": "2026-05-13 09:31",
      "edinet_code": "E22042",
      "sec_code": "21850",
      "doc_url": "https://disclosure2.edinet-fsa.go.jp/WZEK0040.aspx?S1_S100Y2HC"
    },
    {
      "doc_id": "S100XXEO",
      "doc_type": "Large Shareholder Report / Amendment",
      "doc_type_code": "350",
      "category": "Large Shareholder",
      "company_jp": "中村　勇治",
      "company_en": "Yuji Nakamura",
      "description": "大量保有報告書",
      "submitted_at": "2026-05-13 09:34",
      "edinet_code": "E41651",
      "sec_code": null,
      "doc_url": "https://disclosure2.edinet-fsa.go.jp/WZEK0040.aspx?S1_S100XXEO"
    },
    {
      "doc_id": "S100Y2CK",
      "doc_type": "Large Shareholder Report / Amendment",
      "doc_type_code": "350",
      "category": "Large Shareholder",
      "company_jp": "株式会社りそな銀行",
      "company_en": "Resona Bank",
      "description": "大量保有報告書",
      "submitted_at": "2026-05-13 09:37",
      "edinet_code": "E03538",
      "sec_code": null,
      "doc_url": "https://disclosure2.edinet-fsa.go.jp/WZEK0040.aspx?S1_S100Y2CK"
    },
    {
      "doc_id": "S100Y34X",
      "doc_type": "Large Shareholder Report / Amendment",
      "doc_type_code": "350",
      "category": "Large Shareholder",
      "company_jp": "日本成長投資アライアンス株式会社",
      "company_en": "Japan Growth Investment Alliance Co., Ltd.",
      "description": "変更報告書",
      "submitted_at": "2026-05-13 09:37",
      "edinet_code": "E35816",
      "sec_code": null,
      "doc_url": "https://disclosure2.edinet-fsa.go.jp/WZEK0040.aspx?S1_S100Y34X"
    },
    {
      "doc_id": "S100Y1X0",
      "doc_type": "Large Shareholder Report / Amendment",
      "doc_type_code": "350",
      "category": "Large Shareholder",
      "company_jp": "りそなキャピタル株式会社",
      "company_en": "Resona Capital Co., Ltd.",
      "description": "大量保有報告書",
      "submitted_at": "2026-05-13 09:38",
      "edinet_code": "E09995",
      "sec_code": null,
      "doc_url": "https://disclosure2.edinet-fsa.go.jp/WZEK0040.aspx?S1_S100Y1X0"
    },
    {
      "doc_id": "S100XXJ4",
      "doc_type": "Large Shareholder Report / Amendment",
      "doc_type_code": "350",
      "category": "Large Shareholder",
      "company_jp": "中村　賀亮",
      "company_en": "Karyo Nakamura",
      "description": "大量保有報告書",
      "submitted_at": "2026-05-13 09:41",
      "edinet_code": "E41650",
      "sec_code": null,
      "doc_url": "https://disclosure2.edinet-fsa.go.jp/WZEK0040.aspx?S1_S100XXJ4"
    },
    {
      "doc_id": "S100Y3FK",
      "doc_type": "Extraordinary Report (Domestic Specified Securities)",
      "doc_type_code": "180",
      "category": "Extraordinary Report",
      "company_jp": "株式会社鶴見製作所",
      "company_en": "Tsurumi Manufacturing Co., Ltd.",
      "description": "臨時報告書",
      "submitted_at": "2026-05-13 09:46",
      "edinet_code": "E01662",
      "sec_code": "63510",
      "doc_url": "https://disclosure2.edinet-fsa.go.jp/WZEK0040.aspx?S1_S100Y3FK"
    },
    {
      "doc_id": "S100Y3EH",
      "doc_type": "Large Shareholder Report / Amendment",
      "doc_type_code": "350",
      "category": "Large Shareholder",
      "company_jp": "野村證券株式会社",
      "company_en": "Nomura Securities Co., Ltd.",
      "description": "変更報告書",
      "submitted_at": "2026-05-13 09:46",
      "edinet_code": "E03810",
      "sec_code": null,
      "doc_url": "https://disclosure2.edinet-fsa.go.jp/WZEK0040.aspx?S1_S100Y3EH"
    },
    {
      "doc_id": "S100XXIL",
      "doc_type": "Large Shareholder Report / Amendment",
      "doc_type_code": "350",
      "category": "Large Shareholder",
      "company_jp": "中村　尊政",
      "company_en": "Takamasa Nakamura",
      "description": "大量保有報告書",
      "submitted_at": "2026-05-13 09:47",
      "edinet_code": "E41653",
      "sec_code": null,
      "doc_url": "https://disclosure2.edinet-fsa.go.jp/WZEK0040.aspx?S1_S100XXIL"
    },
    {
      "doc_id": "S100Y3G0",
      "doc_type": "Share Buyback Status Report",
      "doc_type_code": "220",
      "category": "Share Buyback",
      "company_jp": "株式会社戸上電機製作所",
      "company_en": "Togami Electric Manufacturing Co., Ltd.",
      "description": "自己株券買付状況報告書（法２４条の６第１項に基づくもの）",
      "submitted_at": "2026-05-13 09:51",
      "edinet_code": "E01747",
      "sec_code": "66430",
      "doc_url": "https://disclosure2.edinet-fsa.go.jp/WZEK0040.aspx?S1_S100Y3G0"
    },
    {
      "doc_id": "S100Y3AY",
      "doc_type": "Share Buyback Status Report",
      "doc_type_code": "220",
      "category": "Share Buyback",
      "company_jp": "スローガン株式会社",
      "company_en": "Slogan Co., Ltd.",
      "description": "自己株券買付状況報告書（法２４条の６第１項に基づくもの）",
      "submitted_at": "2026-05-13 09:53",
      "edinet_code": "E37006",
      "sec_code": "92530",
      "doc_url": "https://disclosure2.edinet-fsa.go.jp/WZEK0040.aspx?S1_S100Y3AY"
    },
    {
      "doc_id": "S100Y3G3",
      "doc_type": "Share Buyback Status Report",
      "doc_type_code": "220",
      "category": "Share Buyback",
      "company_jp": "明和産業株式会社",
      "company_en": "Meiwa Sangyo Co., Ltd.",
      "description": "自己株券買付状況報告書（法２４条の６第１項に基づくもの）",
      "submitted_at": "2026-05-13 09:56",
      "edinet_code": "E02563",
      "sec_code": "81030",
      "doc_url": "https://disclosure2.edinet-fsa.go.jp/WZEK0040.aspx?S1_S100Y3G3"
    },
    {
      "doc_id": "S100Y3FS",
      "doc_type": "Share Buyback Status Report",
      "doc_type_code": "220",
      "category": "Share Buyback",
      "company_jp": "東京海上ホールディングス株式会社",
      "company_en": "Tokio Marine Holdings Co., Ltd.",
      "description": "自己株券買付状況報告書（法２４条の６第１項に基づくもの）",
      "submitted_at": "2026-05-13 10:03",
      "edinet_code": "E03847",
      "sec_code": "87660",
      "doc_url": "https://disclosure2.edinet-fsa.go.jp/WZEK0040.aspx?S1_S100Y3FS"
    },
    {
      "doc_id": "S100Y3GB",
      "doc_type": "Share Buyback Status Report",
      "doc_type_code": "220",
      "category": "Share Buyback",
      "company_jp": "株式会社パイオラックス",
      "company_en": "Piolax Co., Ltd.",
      "description": "自己株券買付状況報告書（法２４条の６第１項に基づくもの）",
      "submitted_at": "2026-05-13 10:06",
      "edinet_code": "E01438",
      "sec_code": "59880",
      "doc_url": "https://disclosure2.edinet-fsa.go.jp/WZEK0040.aspx?S1_S100Y3GB"
    },
    {
      "doc_id": "S100Y2RE",
      "doc_type": "Large Shareholder Report / Amendment",
      "doc_type_code": "350",
      "category": "Large Shareholder",
      "company_jp": "合同会社ＴＯＳ",
      "company_en": "TOS LLC",
      "description": "変更報告書",
      "submitted_at": "2026-05-13 10:07",
      "edinet_code": "E26852",
      "sec_code": null,
      "doc_url": "https://disclosure2.edinet-fsa.go.jp/WZEK0040.aspx?S1_S100Y2RE"
    },
    {
      "doc_id": "S100Y3FF",
      "doc_type": "Share Buyback Status Report",
      "doc_type_code": "220",
      "category": "Share Buyback",
      "company_jp": "エスペック株式会社",
      "company_en": "ESPEC Co., Ltd.",
      "description": "自己株券買付状況報告書（法２４条の６第１項に基づくもの）",
      "submitted_at": "2026-05-13 10:11",
      "edinet_code": "E02307",
      "sec_code": "68590",
      "doc_url": "https://disclosure2.edinet-fsa.go.jp/WZEK0040.aspx?S1_S100Y3FF"
    },
    {
      "doc_id": "S100Y2N4",
      "doc_type": "Large Shareholder Report / Amendment",
      "doc_type_code": "350",
      "category": "Large Shareholder",
      "company_jp": "津田物産株式会社",
      "company_en": "Tsuda Bussan Co., Ltd.",
      "description": "変更報告書",
      "submitted_at": "2026-05-13 10:19",
      "edinet_code": "E26178",
      "sec_code": null,
      "doc_url": "https://disclosure2.edinet-fsa.go.jp/WZEK0040.aspx?S1_S100Y2N4"
    },
    {
      "doc_id": "S100Y3GN",
      "doc_type": "Share Buyback Status Report",
      "doc_type_code": "220",
      "category": "Share Buyback",
      "company_jp": "クリエートメディック株式会社",
      "company_en": "Create Medic Co., Ltd.",
      "description": "自己株券買付状況報告書（法２４条の６第１項に基づくもの）",
      "submitted_at": "2026-05-13 10:20",
      "edinet_code": "E02416",
      "sec_code": "51870",
      "doc_url": "https://disclosure2.edinet-fsa.go.jp/WZEK0040.aspx?S1_S100Y3GN"
    },
    {
      "doc_id": "S100Y368",
      "doc_type": "Large Shareholder Report / Amendment",
      "doc_type_code": "350",
      "category": "Large Shareholder",
      "company_jp": "株式会社みずほ銀行",
      "company_en": "Mizuho Bank, Ltd.",
      "description": "大量保有報告書",
      "submitted_at": "2026-05-13 10:25",
      "edinet_code": "E03532",
      "sec_code": null,
      "doc_url": "https://disclosure2.edinet-fsa.go.jp/WZEK0040.aspx?S1_S100Y368"
    },
    {
      "doc_id": "S100Y369",
      "doc_type": "Large Shareholder Report / Amendment",
      "doc_type_code": "350",
      "category": "Large Shareholder",
      "company_jp": "株式会社みずほ銀行",
      "company_en": "Mizuho Bank, Ltd.",
      "description": "変更報告書",
      "submitted_at": "2026-05-13 10:25",
      "edinet_code": "E03532",
      "sec_code": null,
      "doc_url": "https://disclosure2.edinet-fsa.go.jp/WZEK0040.aspx?S1_S100Y369"
    },
    {
      "doc_id": "S100Y2ZE",
      "doc_type": "Amendment to Large Shareholder Report",
      "doc_type_code": "360",
      "category": "Large Shareholder",
      "company_jp": "西川　啓子",
      "company_en": "Keiko Nishikawa",
      "description": "訂正報告書（大量保有報告書・変更報告書）",
      "submitted_at": "2026-05-13 10:26",
      "edinet_code": "E06321",
      "sec_code": null,
      "doc_url": "https://disclosure2.edinet-fsa.go.jp/WZEK0040.aspx?S1_S100Y2ZE"
    },
    {
      "doc_id": "S100Y384",
      "doc_type": "Large Shareholder Report / Amendment",
      "doc_type_code": "350",
      "category": "Large Shareholder",
      "company_jp": "みずほ証券株式会社",
      "company_en": "Mizuho Securities Co., Ltd.",
      "description": "変更報告書",
      "submitted_at": "2026-05-13 10:27",
      "edinet_code": "E03759",
      "sec_code": null,
      "doc_url": "https://disclosure2.edinet-fsa.go.jp/WZEK0040.aspx?S1_S100Y384"
    },
    {
      "doc_id": "S100Y212",
      "doc_type": "Large Shareholder Report / Amendment",
      "doc_type_code": "350",
      "category": "Large Shareholder",
      "company_jp": "株式会社フォワードＴ",
      "company_en": "Forward T Co., Ltd.",
      "description": "変更報告書",
      "submitted_at": "2026-05-13 10:28",
      "edinet_code": "E21953",
      "sec_code": null,
      "doc_url": "https://disclosure2.edinet-fsa.go.jp/WZEK0040.aspx?S1_S100Y212"
    },
    {
      "doc_id": "S100Y37F",
      "doc_type": "Large Shareholder Report / Amendment",
      "doc_type_code": "350",
      "category": "Large Shareholder",
      "company_jp": "みずほ信託銀行株式会社",
      "company_en": "Mizuho Trust and Banking Co., Ltd.",
      "description": "大量保有報告書",
      "submitted_at": "2026-05-13 10:29",
      "edinet_code": "E03628",
      "sec_code": null,
      "doc_url": "https://disclosure2.edinet-fsa.go.jp/WZEK0040.aspx?S1_S100Y37F"
    },
    {
      "doc_id": "S100Y3F9",
      "doc_type": "Extraordinary Report (Domestic Specified Securities)",
      "doc_type_code": "180",
      "category": "Extraordinary Report",
      "company_jp": "ソフトバンクグループ株式会社",
      "company_en": "SoftBank Group Corp.",
      "description": "臨時報告書",
      "submitted_at": "2026-05-13 10:30",
      "edinet_code": "E02778",
      "sec_code": "99840",
      "doc_url": "https://disclosure2.edinet-fsa.go.jp/WZEK0040.aspx?S1_S100Y3F9"
    }
  ]
}